khaos/__init__.py
khaos/cli.py
khaos/defaults.py
khaos/errors.py
khaos/executor/__init__.py
khaos/executor/base.py
khaos/executor/external.py
khaos/executor/incident_scheduler.py
khaos/executor/local.py
khaos/executor/result.py
khaos/executor/serializer.py
khaos/executor/simulator_factory.py
khaos/executor/stats.py
khaos/executor/topic_manager.py
khaos/generators/__init__.py
khaos/generators/field.py
khaos/generators/flow.py
khaos/generators/key.py
khaos/generators/payload.py
khaos/generators/schema.py
khaos/infrastructure/__init__.py
khaos/infrastructure/compose_runner.py
khaos/infrastructure/docker_manager.py
khaos/infrastructure/schema_registry_manager.py
khaos/kafka/__init__.py
khaos/kafka/admin.py
khaos/kafka/config.py
khaos/kafka/consumer.py
khaos/kafka/dlq.py
khaos/kafka/producer.py
khaos/kafka/simulator.py
khaos/models/__init__.py
khaos/models/cluster.py
khaos/models/config.py
khaos/models/flow.py
khaos/models/message.py
khaos/models/schema.py
khaos/models/topic.py
khaos/scenarios/__init__.py
khaos/scenarios/incidents.py
khaos/scenarios/loader.py
khaos/scenarios/parser.py
khaos/scenarios/scenario.py
khaos/serialization/__init__.py
khaos/serialization/avro.py
khaos/serialization/base.py
khaos/serialization/json.py
khaos/serialization/protobuf.py
khaos/serialization/schema_converter.py
khaos/validators/__init__.py
khaos/validators/common.py
khaos/validators/flow.py
khaos/validators/scenario.py
khaos/validators/schema.py
khaos/bundled_docker/docker-compose.kraft.yml
khaos/bundled_docker/docker-compose.schema-registry.kraft.yml
khaos/bundled_docker/docker-compose.schema-registry.zk.yml
khaos/bundled_docker/docker-compose.zk.yml
khaos/bundled_scenarios/chaos/all-incidents.yaml
khaos/bundled_scenarios/chaos/broker-chaos.yaml
khaos/bundled_scenarios/chaos/chaos-loop.yaml
khaos/bundled_scenarios/chaos/leadership-churn.yaml
khaos/bundled_scenarios/chaos/rebalance-storm.yaml
khaos/bundled_scenarios/chaos/targeted-incidents.yaml
khaos_cli-0.7.1.dist-info/METADATA
khaos_cli-0.7.1.dist-info/WHEEL
khaos_cli-0.7.1.dist-info/entry_points.txt
khaos_cli-0.7.1.dist-info/licenses/LICENSE
khaos_cli-0.7.1.dist-info/RECORD
