Metadata-Version: 2.4
Name: khaos-cli
Version: 0.7.1
Summary: Kafka data generator and load testing tool - generate fake messages, simulate producers and consumers, test broker failures, and run chaos engineering scenarios
Project-URL: Homepage, https://github.com/aleksandarskrbic/khaos
Project-URL: Repository, https://github.com/aleksandarskrbic/khaos
Project-URL: Issues, https://github.com/aleksandarskrbic/khaos/issues
Author-email: Aleksandar Skrbic <aleksandarskrbic@gmail.com>
License-Expression: Apache-2.0
License-File: LICENSE
Keywords: chaos-engineering,data-generator,event-streaming,fake-data,fault-injection,flink,kafka,kafka-consumer,kafka-data-generator,kafka-load-testing,kafka-producer,kafka-streams,kafka-testing,load-testing,message-queue,spark-streaming,stream-processing,stress-testing,synthetic-data,test-data
Requires-Python: >=3.11
Requires-Dist: confluent-kafka[protobuf,schemaregistry]>=2.3.0
Requires-Dist: faker>=33.0.0
Requires-Dist: fastavro>=1.9.0
Requires-Dist: protobuf>=4.21.0
Requires-Dist: pyyaml>=6.0.3
Requires-Dist: rich>=13.0.0
Requires-Dist: typer>=0.20.0
